LICENSE.md
MANIFEST.in
README.md
README.rst
pyproject.toml
setup.py
nnmnkwii/__init__.py
nnmnkwii/version.py
nnmnkwii.egg-info/PKG-INFO
nnmnkwii.egg-info/SOURCES.txt
nnmnkwii.egg-info/dependency_links.txt
nnmnkwii.egg-info/requires.txt
nnmnkwii.egg-info/top_level.txt
nnmnkwii/autograd/__init__.py
nnmnkwii/autograd/_impl/__init__.py
nnmnkwii/autograd/_impl/mlpg.py
nnmnkwii/autograd/_impl/modspec.py
nnmnkwii/baseline/__init__.py
nnmnkwii/baseline/gmm.py
nnmnkwii/datasets/__init__.py
nnmnkwii/datasets/cmu_arctic.py
nnmnkwii/datasets/jsut.py
nnmnkwii/datasets/jvs.py
nnmnkwii/datasets/ljspeech.py
nnmnkwii/datasets/vcc2016.py
nnmnkwii/datasets/vctk.py
nnmnkwii/datasets/voice_statistics.py
nnmnkwii/frontend/__init__.py
nnmnkwii/frontend/merlin.py
nnmnkwii/functions/__init__.py
nnmnkwii/io/__init__.py
nnmnkwii/io/hts.py
nnmnkwii/metrics/__init__.py
nnmnkwii/paramgen/__init__.py
nnmnkwii/paramgen/_mlpg.py
nnmnkwii/paramgen/mlpg_helper.pyx
nnmnkwii/paramgen/_bandmat/License
nnmnkwii/paramgen/_bandmat/__init__.py
nnmnkwii/paramgen/_bandmat/core.pyx
nnmnkwii/paramgen/_bandmat/full.pyx
nnmnkwii/paramgen/_bandmat/linalg.pyx
nnmnkwii/paramgen/_bandmat/overlap.pyx
nnmnkwii/paramgen/_bandmat/tensor.pyx
nnmnkwii/paramgen/_bandmat/testhelp.py
nnmnkwii/postfilters/__init__.py
nnmnkwii/preprocessing/__init__.py
nnmnkwii/preprocessing/alignment.py
nnmnkwii/preprocessing/f0.py
nnmnkwii/preprocessing/generic.py
nnmnkwii/preprocessing/modspec.py
nnmnkwii/util/__init__.py
nnmnkwii/util/_linalg.pyx
nnmnkwii/util/files.py
nnmnkwii/util/linalg.py
nnmnkwii/util/_example_data/COPYING
nnmnkwii/util/_example_data/arctic_a0009.wav
nnmnkwii/util/_example_data/arctic_a0009_phone.lab
nnmnkwii/util/_example_data/arctic_a0009_state.lab
nnmnkwii/util/_example_data/questions-radio_dnn_416.hed
nnmnkwii/util/_example_data/slt_arctic_demo_data/X_acoustic/arctic_a0001.npz
nnmnkwii/util/_example_data/slt_arctic_demo_data/X_acoustic/arctic_a0002.npz
nnmnkwii/util/_example_data/slt_arctic_demo_data/X_acoustic/arctic_a0003.npz
nnmnkwii/util/_example_data/slt_arctic_demo_data/X_duration/arctic_a0001.npz
